[
  {
    "name": "MP7 | Vault Heist (Minimal Wear)",
    "price": 1.36,
    "wear": "Minimal Wear",
    "stattrak": false,
    "souvenir": false,
    "item_name": "MP7 | Vault Heist",
    "id": "skin-2166716"
  },
  {
    "name": "MP7 | Vault Heist (Factory New)",
    "price": 1.41,
    "wear": "Factory New",
    "stattrak": false,
    "souvenir": false,
    "item_name": "MP7 | Vault Heist",
    "id": "skin-2166716"
  },
  {
    "name": "MP7 | Vault Heist (Battle-Scarred)",
    "price": 1.19,
    "wear": "Battle-Scarred",
    "stattrak": false,
    "souvenir": false,
    "item_name": "MP7 | Vault Heist",
    "id": "skin-2166716"
  },
  {
    "name": "MP7 | Vault Heist (Field-Tested)",
    "price": 1.17,
    "wear": "Field-Tested",
    "stattrak": false,
    "souvenir": false,
    "item_name": "MP7 | Vault Heist",
    "id": "skin-2166716"
  },
  {
    "name": "MP7 | Vault Heist (Well-Worn)",
    "price": 1.2,
    "wear": "Well-Worn",
    "stattrak": false,
    "souvenir": false,
    "item_name": "MP7 | Vault Heist",
    "id": "skin-2166716"
  }
]