[
  {
    "name": "★ Bayonet | Urban Masked (Minimal Wear)",
    "price": 209.4,
    "wear": "Minimal Wear",
    "stattrak": false,
    "souvenir": false,
    "item_name": "★ Bayonet | Urban Masked",
    "id": "skin-32768572"
  },
  {
    "name": "★ StatTrak™ Bayonet | Urban Masked (Field-Tested)",
    "price": 164.15,
    "wear": "Field-Tested",
    "stattrak": true,
    "souvenir": false,
    "item_name": "★ Bayonet | Urban Masked",
    "id": "skin-32768572"
  },
  {
    "name": "★ StatTrak™ Bayonet | Urban Masked (Factory New)",
    "price": 0,
    "wear": "Factory New",
    "stattrak": true,
    "souvenir": false,
    "item_name": "★ Bayonet | Urban Masked",
    "id": "skin-32768572"
  },
  {
    "name": "★ Bayonet | Urban Masked (Battle-Scarred)",
    "price": 160.72,
    "wear": "Battle-Scarred",
    "stattrak": false,
    "souvenir": false,
    "item_name": "★ Bayonet | Urban Masked",
    "id": "skin-32768572"
  },
  {
    "name": "★ StatTrak™ Bayonet | Urban Masked (Minimal Wear)",
    "price": 246.77,
    "wear": "Minimal Wear",
    "stattrak": true,
    "souvenir": false,
    "item_name": "★ Bayonet | Urban Masked",
    "id": "skin-32768572"
  },
  {
    "name": "★ StatTrak™ Bayonet | Urban Masked (Battle-Scarred)",
    "price": 190.61,
    "wear": "Battle-Scarred",
    "stattrak": true,
    "souvenir": false,
    "item_name": "★ Bayonet | Urban Masked",
    "id": "skin-32768572"
  },
  {
    "name": "★ Bayonet | Urban Masked (Well-Worn)",
    "price": 164.49,
    "wear": "Well-Worn",
    "stattrak": false,
    "souvenir": false,
    "item_name": "★ Bayonet | Urban Masked",
    "id": "skin-32768572"
  },
  {
    "name": "★ StatTrak™ Bayonet | Urban Masked (Well-Worn)",
    "price": 239.98,
    "wear": "Well-Worn",
    "stattrak": true,
    "souvenir": false,
    "item_name": "★ Bayonet | Urban Masked",
    "id": "skin-32768572"
  },
  {
    "name": "★ Bayonet | Urban Masked (Factory New)",
    "price": 360.31,
    "wear": "Factory New",
    "stattrak": false,
    "souvenir": false,
    "item_name": "★ Bayonet | Urban Masked",
    "id": "skin-32768572"
  },
  {
    "name": "★ Bayonet | Urban Masked (Field-Tested)",
    "price": 165.93,
    "wear": "Field-Tested",
    "stattrak": false,
    "souvenir": false,
    "item_name": "★ Bayonet | Urban Masked",
    "id": "skin-32768572"
  }
]