[
  {
    "name": "★ StatTrak™ Falchion Knife | Lore (Factory New)",
    "price": 260.48,
    "wear": "Factory New",
    "stattrak": true,
    "souvenir": false,
    "item_name": "★ Falchion Knife | Lore",
    "id": "skin-33558856"
  },
  {
    "name": "★ Falchion Knife | Lore (Well-Worn)",
    "price": 156.33,
    "wear": "Well-Worn",
    "stattrak": false,
    "souvenir": false,
    "item_name": "★ Falchion Knife | Lore",
    "id": "skin-33558856"
  },
  {
    "name": "★ StatTrak™ Falchion Knife | Lore (Well-Worn)",
    "price": 198.84,
    "wear": "Well-Worn",
    "stattrak": true,
    "souvenir": false,
    "item_name": "★ Falchion Knife | Lore",
    "id": "skin-33558856"
  },
  {
    "name": "★ Falchion Knife | Lore (Minimal Wear)",
    "price": 196.1,
    "wear": "Minimal Wear",
    "stattrak": false,
    "souvenir": false,
    "item_name": "★ Falchion Knife | Lore",
    "id": "skin-33558856"
  },
  {
    "name": "★ Falchion Knife | Lore (Factory New)",
    "price": 242.04,
    "wear": "Factory New",
    "stattrak": false,
    "souvenir": false,
    "item_name": "★ Falchion Knife | Lore",
    "id": "skin-33558856"
  },
  {
    "name": "★ StatTrak™ Falchion Knife | Lore (Field-Tested)",
    "price": 164.56,
    "wear": "Field-Tested",
    "stattrak": true,
    "souvenir": false,
    "item_name": "★ Falchion Knife | Lore",
    "id": "skin-33558856"
  },
  {
    "name": "★ StatTrak™ Falchion Knife | Lore (Minimal Wear)",
    "price": 198.84,
    "wear": "Minimal Wear",
    "stattrak": true,
    "souvenir": false,
    "item_name": "★ Falchion Knife | Lore",
    "id": "skin-33558856"
  },
  {
    "name": "★ Falchion Knife | Lore (Field-Tested)",
    "price": 158.8,
    "wear": "Field-Tested",
    "stattrak": false,
    "souvenir": false,
    "item_name": "★ Falchion Knife | Lore",
    "id": "skin-33558856"
  },
  {
    "name": "★ Falchion Knife | Lore (Battle-Scarred)",
    "price": 130.12,
    "wear": "Battle-Scarred",
    "stattrak": false,
    "souvenir": false,
    "item_name": "★ Falchion Knife | Lore",
    "id": "skin-33558856"
  },
  {
    "name": "★ StatTrak™ Falchion Knife | Lore (Battle-Scarred)",
    "price": 178.27,
    "wear": "Battle-Scarred",
    "stattrak": true,
    "souvenir": false,
    "item_name": "★ Falchion Knife | Lore",
    "id": "skin-33558856"
  }
]