[
  {
    "name": "★ Hydra Gloves | Case Hardened (Factory New)",
    "price": 642.99,
    "wear": "Factory New",
    "stattrak": false,
    "souvenir": false,
    "item_name": "★ Hydra Gloves | Case Hardened",
    "id": "skin-330014000"
  },
  {
    "name": "★ Hydra Gloves | Case Hardened (Well-Worn)",
    "price": 77.96,
    "wear": "Well-Worn",
    "stattrak": false,
    "souvenir": false,
    "item_name": "★ Hydra Gloves | Case Hardened",
    "id": "skin-330014000"
  },
  {
    "name": "★ Hydra Gloves | Case Hardened (Minimal Wear)",
    "price": 135.76,
    "wear": "Minimal Wear",
    "stattrak": false,
    "souvenir": false,
    "item_name": "★ Hydra Gloves | Case Hardened",
    "id": "skin-330014000"
  },
  {
    "name": "★ Hydra Gloves | Case Hardened (Battle-Scarred)",
    "price": 65.82,
    "wear": "Battle-Scarred",
    "stattrak": false,
    "souvenir": false,
    "item_name": "★ Hydra Gloves | Case Hardened",
    "id": "skin-330014000"
  },
  {
    "name": "★ Hydra Gloves | Case Hardened (Field-Tested)",
    "price": 81.94,
    "wear": "Field-Tested",
    "stattrak": false,
    "souvenir": false,
    "item_name": "★ Hydra Gloves | Case Hardened",
    "id": "skin-330014000"
  }
]